trddatetime/__init__.py
trddatetime/base.py
trddatetime/krx.py
trddatetime/us.py
trddatetime-0.0.0.dist-info/LICENSE
trddatetime-0.0.0.dist-info/METADATA
trddatetime-0.0.0.dist-info/WHEEL
trddatetime-0.0.0.dist-info/top_level.txt
trddatetime-0.0.0.dist-info/RECORD
