Metadata-Version: 2.1
Name: trddatetime
Version: 0.0.0
Summary: TradeDatetime
Home-page: https://github.com/innovata/trddatetime
Author: innovata sambong
Author-email: iinnovata@gmail.com
License: UNKNOWN
Platform: UNKNOWN
Classifier: Programming Language :: Python :: 3
Classifier: License :: OSI Approved :: MIT License
Classifier: Operating System :: OS Independent
Requires-Python: >=3.8
License-File: LICENSE
